bin/cufinufft.dll
bin/__init__.py
cufinufft/_compat.py
cufinufft/_cufinufft.py
cufinufft/_plan.py
cufinufft/_simple.py
cufinufft/__init__.py
cufinufft-2.4.1.dist-info/DELVEWHEEL
cufinufft-2.4.1.dist-info/METADATA
cufinufft-2.4.1.dist-info/RECORD
cufinufft-2.4.1.dist-info/WHEEL
cufinufft.libs/.load-order-cufinufft-2.4.1
cufinufft.libs/msvcp140-38fc61425eb4b3dd092b0e154c0b1cad.dll
cufinufft.libs/vcruntime140-89e173503c997fe770eb3244f8648b16.dll
cufinufft.libs/vcruntime140_1-06f01871209ce1571ed887dcf20423e2.dll
include/cufinufft.h
include/cufinufft_opts.h
include/__init__.py
lib/cufinufft.lib
lib/__init__.py
