Metadata-Version: 2.1
Name: cufinufft
Version: 2.4.1
Summary: Non-uniform fast Fourier transforms on the GPU
Author: Yu-shuan Melody Shih, Garrett Wright, Joakim Anden, Marco Barbone, Robert Blackwell, Johannes Blascke, Alex Barnett
Maintainer-Email: Joakim Anden <janden-vscholar@flatironinstitute.org>
Classifier: Intended Audience :: Science/Research
Classifier: License :: OSI Approved :: Apache Software License
Classifier: Programming Language :: Python :: 3
Classifier: Programming Language :: C++
Classifier: Operating System :: POSIX :: Linux
Classifier: Environment :: GPU
Classifier: Topic :: Scientific/Engineering :: Mathematics
Requires-Python: >=3.8
Requires-Dist: numpy
Requires-Dist: packaging
